adam_ascii/__init__.py
adam_ascii/interface.py
adam_ascii/py.typed
adam_ascii-0.4.0.dist-info/LICENSE
adam_ascii-0.4.0.dist-info/METADATA
adam_ascii-0.4.0.dist-info/WHEEL
adam_ascii-0.4.0.dist-info/entry_points.txt
adam_ascii-0.4.0.dist-info/RECORD
