Metadata-Version: 2.1
Name: adam-ascii
Version: 0.4.0
Summary: asyncio python interface for Advantech ADAM modules
License: MIT
Author: Josh Gruenstein
Author-email: josh@tutorintelligence.com
Requires-Python: >=3.10,<4.0
Classifier: License :: OSI Approved :: MIT License
Classifier: Programming Language :: Python :: 3
Classifier: Programming Language :: Python :: 3.10
Classifier: Programming Language :: Python :: 3.11
Classifier: Programming Language :: Python :: 3.12
